./.gitignore
./.pre-commit-config.yaml
./LICENSE
./PKG-INFO
./README.md
./cli.py
./config.py
./core.py
./pyproject.toml
./run_ww.sh
./uv.lock
./.github/workflows/ci.yml
./.github/workflows/publish.yml
ww_manager-2.0.6.dist-info/METADATA
ww_manager-2.0.6.dist-info/WHEEL
ww_manager-2.0.6.dist-info/entry_points.txt
ww_manager-2.0.6.dist-info/licenses/LICENSE
ww_manager-2.0.6.dist-info/RECORD
