Metadata-Version: 2.4
Name: ww-manager
Version: 2.0.6
Summary: 鸣潮命令行管理器
License-File: LICENSE
Requires-Python: >=3.9
Requires-Dist: certifi
Requires-Dist: rich
Requires-Dist: tqdm
Requires-Dist: typer
